hami/_C.cpython-39-x86_64-linux-gnu.so
hami/__init__.py
hami/_build_info.py
hami/_version.py
hami/commands.py
hami/libhami.so
hami/parser.py
hami/_C/__init__.pyi
hami/_C/backend.pyi
hami/_C/base_types.pyi
hami/csrc/all2numpy.hpp
hami/csrc/any.hpp
hami/csrc/atomic_type.hpp
hami/csrc/backend.hpp
hami/csrc/box.hpp
hami/csrc/converts.hpp
hami/csrc/dict.hpp
hami/csrc/py_helper.hpp
hami/csrc/py_register.hpp
hami/csrc/python.hpp
hami/csrc/register.hpp
hami/include/hami/extension.hpp
hami/include/hami/builtin/aspect.hpp
hami/include/hami/builtin/basic_backends.hpp
hami/include/hami/builtin/benchmark.hpp
hami/include/hami/builtin/box.hpp
hami/include/hami/builtin/cat_split.hpp
hami/include/hami/builtin/condition.hpp
hami/include/hami/builtin/control_plane.hpp
hami/include/hami/builtin/generate_backend.hpp
hami/include/hami/builtin/identity.hpp
hami/include/hami/builtin/interpreter.hpp
hami/include/hami/builtin/ioc.hpp
hami/include/hami/builtin/key_operator.hpp
hami/include/hami/builtin/launch.hpp
hami/include/hami/builtin/or.hpp
hami/include/hami/builtin/page_table.hpp
hami/include/hami/builtin/proxy.hpp
hami/include/hami/builtin/register_node.hpp
hami/include/hami/builtin/result_parser.hpp
hami/include/hami/builtin/result_queue.hpp
hami/include/hami/builtin/select.hpp
hami/include/hami/builtin/sequential.hpp
hami/include/hami/builtin/source.hpp
hami/include/hami/builtin/tree.hpp
hami/include/hami/core/any.hpp
hami/include/hami/core/backend.hpp
hami/include/hami/core/dict.hpp
hami/include/hami/core/event.hpp
hami/include/hami/core/general_queue.hpp
hami/include/hami/core/helper.hpp
hami/include/hami/core/parser.hpp
hami/include/hami/core/queue.hpp
hami/include/hami/core/reflect.h
hami/include/hami/core/request_size.hpp
hami/include/hami/core/string.hpp
hami/include/hami/core/task_keys.hpp
hami/include/hami/helper/base_logging.hpp
hami/include/hami/helper/exception.hpp
hami/include/hami/helper/filesystem.hpp
hami_core-1.40.0.dist-info/METADATA
hami_core-1.40.0.dist-info/WHEEL
hami_core-1.40.0.dist-info/top_level.txt
hami_core-1.40.0.dist-info/RECORD
hami_core-1.40.0.dist-info/licenses/LICENSE
