Metadata-Version: 2.4
Name: hami-core
Version: 1.40.0
Summary: A Python library for batched backend scheduling
Author-email: torchpipe Team <hydzhang@hotmail.com>
License: Apache-2.0
Project-URL: Homepage, https://github.com/torchpipe/torchpipe
Classifier: Development Status :: 3 - Alpha
Classifier: Intended Audience :: Developers
Classifier: Intended Audience :: Education
Classifier: Programming Language :: C++
Classifier: Programming Language :: Python :: 3 :: Only
Classifier: Operating System :: POSIX :: Linux
Classifier: License :: OSI Approved :: Apache Software License
Classifier: Topic :: Scientific/Engineering
Classifier: Topic :: Scientific/Engineering :: Artificial Intelligence
Requires-Python: >=3.8
License-File: LICENSE
Requires-Dist: tomli>=2.0.1; python_version < "3.14"
Requires-Dist: numpy>=1.19
Dynamic: license-file
